{"parser": "github", "uid": "github/OliverFHD/GPUniverse", "url": "https://github.com/OliverFHD/GPUniverse", "data": {"doi": ["https://ui.adsabs.harvard.edu/abs/2022CQGra..39w5012F", "https://ui.adsabs.harvard.edu/abs/2024ascl.soft04018F/abstract"], "title": "GPUniverse: Quantum fields in finite dimensional Hilbert spaces modeler", "url": "https://github.com/OliverFHD/GPUniverse", "name": "GPUniverse", "full_name": "OliverFHD/GPUniverse", "html_url": "https://github.com/OliverFHD/GPUniverse", "description": "Modelling holographic quantum fields in finite dimensional Hilbert spaces with Generalised Pauli Operators (GPOs) and overlapping degrees of freedom. Also: simulate overlapping qubits with GPUs.", "created_at": "2021-11-05T15:31:52Z", "updated_at": "2024-04-25T07:40:59Z", "clone_url": "https://github.com/OliverFHD/GPUniverse.git", "size": 3002, "stargazers_count": 1, "watchers_count": 1, "language": "Jupyter Notebook", "subscribers_count": 1, "owner": {"html_url": "https://github.com/OliverFHD", "avatar_url": "https://avatars.githubusercontent.com/u/16794844?v=4", "login": "OliverFHD", "type": "User"}, "timestamp": "2024-05-05 00:36:21.196934", "avatar": "https://avatars.githubusercontent.com/u/16794844?v=4"}}
