{
    "parser": "github",
    "uid": "github/thegenemyers/FASTK",
    "url": "https://github.com/thegenemyers/FASTK",
    "data": {
        "title": "FastK",
        "url": "https://github.com/thegenemyers/FASTK",
        "credit": [],
        "tags": [
            "high-throughput-sequencing"
        ],
        "description": "A fast K-mer counter for high-fidelity shotgun datasets",
        "name": "FASTK",
        "full_name": "thegenemyers/FASTK",
        "html_url": "https://github.com/thegenemyers/FASTK",
        "created_at": "2020-10-19T21:11:00Z",
        "updated_at": "2025-04-23T18:05:22Z",
        "clone_url": "https://github.com/thegenemyers/FASTK.git",
        "size": 12385,
        "stargazers_count": 125,
        "watchers_count": 125,
        "language": "C",
        "open_issues_count": 18,
        "license": {
            "key": "other",
            "name": "Other",
            "spdx_id": "NOASSERTION",
            "url": null,
            "node_id": "MDc6TGljZW5zZTA="
        },
        "subscribers_count": 10,
        "owner": {
            "html_url": "https://github.com/thegenemyers",
            "avatar_url": "https://avatars.githubusercontent.com/u/6890550?v=4",
            "login": "thegenemyers",
            "type": "User"
        },
        "timestamp": "2025-04-27 00:54:57.114154",
        "avatar": "https://avatars.githubusercontent.com/u/6890550?v=4"
    }
}