{"parser": "github", "uid": "github/exoclime/FastChem", "url": "https://github.com/exoclime/FastChem", "data": {"doi": ["https://ui.adsabs.harvard.edu/abs/2018ApJ...863..183K", "https://ui.adsabs.harvard.edu/abs/2018MNRAS.479..865S", "https://ui.adsabs.harvard.edu/abs/2018ascl.soft04025K/abstract"], "title": "FastChem: An ultra-fast equilibrium chemistry", "url": "https://github.com/exoclime/FastChem", "name": "FastChem", "full_name": "exoclime/FastChem", "html_url": "https://github.com/exoclime/FastChem", "description": "An ultra-fast equilibrium chemistry", "created_at": "2017-12-30T16:59:57Z", "updated_at": "2022-07-13T15:11:13Z", "clone_url": "https://github.com/exoclime/FastChem.git", "size": 5879, "stargazers_count": 18, "watchers_count": 18, "language": "C++", "license": {"key": "gpl-3.0", "name": "GNU General Public License v3.0", "spdx_id": "GPL-3.0", "url": "https://api.github.com/licenses/gpl-3.0", "node_id": "MDc6TGljZW5zZTk="}, "subscribers_count": 6, "owner": {"html_url": "https://github.com/exoclime", "avatar_url": "https://avatars.githubusercontent.com/u/61202311?v=4", "login": "exoclime", "type": "Organization"}, "timestamp": "2022-07-17 17:18:55.003695", "avatar": "https://avatars.githubusercontent.com/u/61202311?v=4"}}
