{"parser": "github", "uid": "github/connor-makowski/type_enforced", "url": "https://github.com/connor-makowski/type_enforced", "data": {"doi": "https://doi.org/10.5281/zenodo.17184819", "name": "type_enforced", "url": "https://github.com/connor-makowski/type_enforced", "full_name": "connor-makowski/type_enforced", "html_url": "https://github.com/connor-makowski/type_enforced", "description": "A pure python runtime type enforcer for annotations. Enforce types in python functions and methods.", "created_at": "2022-04-15T14:13:09Z", "updated_at": "2025-10-02T14:48:06Z", "clone_url": "https://github.com/connor-makowski/type_enforced.git", "size": 3426, "stargazers_count": 59, "watchers_count": 59, "language": "Python", "open_issues_count": 4, "license": {"key": "mit", "name": "MIT License", "spdx_id": "MIT", "url": "https://api.github.com/licenses/mit", "node_id": "MDc6TGljZW5zZTEz"}, "subscribers_count": 2, "owner": {"html_url": "https://github.com/connor-makowski", "avatar_url": "https://avatars.githubusercontent.com/u/32932187?v=4", "login": "connor-makowski", "type": "User"}, "timestamp": "2025-10-05 00:53:01.707384", "avatar": "https://avatars.githubusercontent.com/u/32932187?v=4"}}
