{"parser": "github", "uid": "github/adbar/htmldate", "url": "https://api.github.com/repos/adbar/htmldate", "data": {"timestamp": "2020-08-02 16:35:22.431046", "name": "htmldate", "url": "https://api.github.com/repos/adbar/htmldate", "full_name": "adbar/htmldate", "html_url": "https://github.com/adbar/htmldate", "private": false, "description": "Fast and robust date extraction from web pages, from the command-line or within Python", "created_at": "2017-08-24T14:09:12Z", "updated_at": "2020-07-30T13:58:01Z", "clone_url": "https://github.com/adbar/htmldate.git", "homepage": "https://htmldate.readthedocs.io", "size": 5674, "stargazers_count": 14, "watchers_count": 14, "language": "Python", "open_issues_count": 5, "license": {"key": "gpl-3.0", "name": "GNU General Public License v3.0", "spdx_id": "GPL-3.0", "url": "https://api.github.com/licenses/gpl-3.0", "node_id": "MDc6TGljZW5zZTk="}, "subscribers_count": 2, "owner": {"html_url": "https://github.com/adbar", "avatar_url": "https://avatars0.githubusercontent.com/u/2125866?v=4", "login": "adbar", "type": "User"}}, "doi": "https://doi.org/10.5281/zenodo.3966235", "name": "htmldate", "full_name": "adbar/htmldate", "html_url": "https://github.com/adbar/htmldate", "private": false, "description": "Fast and robust date extraction from web pages, from the command-line or within Python", "created_at": "2017-08-24T14:09:12Z", "updated_at": "2020-08-22T06:23:55Z", "clone_url": "https://github.com/adbar/htmldate.git", "homepage": "https://htmldate.readthedocs.io", "size": 5674, "stargazers_count": 15, "watchers_count": 15, "language": "Python", "open_issues_count": 6, "license": {"key": "gpl-3.0", "name": "GNU General Public License v3.0", "spdx_id": "GPL-3.0", "url": "https://api.github.com/licenses/gpl-3.0", "node_id": "MDc6TGljZW5zZTk="}, "subscribers_count": 3, "owner": {"html_url": "https://github.com/adbar", "avatar_url": "https://avatars0.githubusercontent.com/u/2125866?v=4", "login": "adbar", "type": "User"}, "topics": ["metadata-extraction", "date-parser", "html-parsing", "entity-extraction", "natural-language-processing", "nlp", "web-scraping", "webscraping", "date", "datetime", "metadata", "information-extraction"]}
