{
    "parser": "github",
    "uid": "github/LCOGT/banzai-nres",
    "url": "https://github.com/LCOGT/banzai-nres",
    "data": {
        "doi": [
            "https://ui.adsabs.harvard.edu/abs/2022AJ....164..152S",
            "https://ui.adsabs.harvard.edu/abs/2022SPIE12189E..14M",
            "https://ui.adsabs.harvard.edu/abs/2022ascl.soft12012M/abstract"
        ],
        "title": "BANZAI-NRES: BANZAI data reduction pipeline for NRES",
        "url": "https://github.com/LCOGT/banzai-nres",
        "name": "banzai-nres",
        "full_name": "LCOGT/banzai-nres",
        "html_url": "https://github.com/LCOGT/banzai-nres",
        "description": "BANZAI Data Reduction Pipeline for NRES",
        "created_at": "2018-07-13T15:44:06Z",
        "updated_at": "2022-12-08T01:05:32Z",
        "clone_url": "https://github.com/LCOGT/banzai-nres.git",
        "size": 21548,
        "stargazers_count": 3,
        "watchers_count": 3,
        "language": "Python",
        "open_issues_count": 7,
        "subscribers_count": 5,
        "owner": {
            "html_url": "https://github.com/LCOGT",
            "avatar_url": "https://avatars.githubusercontent.com/u/3358238?v=4",
            "login": "LCOGT",
            "type": "Organization"
        },
        "topics": [
            "backend"
        ],
        "timestamp": "2023-01-01 00:39:34.124556",
        "avatar": "https://avatars.githubusercontent.com/u/3358238?v=4"
    }
}