{"parser": "github", "uid": "github/synchrofit/synchrofit", "url": "https://github.com/synchrofit/synchrofit", "data": {"doi": [], "title": "synchrofit: Python-based synchrotron spectral fitting", "url": "https://github.com/synchrofit/synchrofit", "name": "synchrofit", "full_name": "synchrofit/synchrofit", "html_url": "https://github.com/synchrofit/synchrofit", "description": "Code for modelling a radio spectrum using the JP, KP or CI models. ", "created_at": "2021-02-23T08:57:40Z", "updated_at": "2022-06-02T03:14:34Z", "clone_url": "https://github.com/synchrofit/synchrofit.git", "size": 468, "stargazers_count": 13, "watchers_count": 13, "language": "Python", "open_issues_count": 1, "license": {"key": "mit", "name": "MIT License", "spdx_id": "MIT", "url": "https://api.github.com/licenses/mit", "node_id": "MDc6TGljZW5zZTEz"}, "subscribers_count": 1, "owner": {"html_url": "https://github.com/synchrofit", "avatar_url": "https://avatars.githubusercontent.com/u/79506129?v=4", "login": "synchrofit", "type": "Organization"}, "timestamp": "2022-07-17 17:12:37.186039", "avatar": "https://avatars.githubusercontent.com/u/79506129?v=4"}}
