{"parser": "github", "uid": "github/cthoyt/bel-resources", "url": "https://github.com/pybel/bel-resources", "data": {"url": "https://github.com/pybel/bel-resources", "title": "Python3-bel-resources", "description": "Utilities for BEL resource files.", "name": "bel-resources", "full_name": "pybel/bel-resources", "html_url": "https://github.com/pybel/bel-resources", "created_at": "2019-01-05T22:02:47Z", "updated_at": "2019-11-15T13:44:22Z", "clone_url": "https://github.com/pybel/bel-resources.git", "size": 42, "language": "Python", "license": {"key": "mit", "name": "MIT License", "spdx_id": "MIT", "url": "https://api.github.com/licenses/mit", "node_id": "MDc6TGljZW5zZTEz"}, "subscribers_count": 2, "owner": {"html_url": "https://github.com/pybel", "avatar_url": "https://avatars.githubusercontent.com/u/22892058?v=4", "login": "pybel", "type": "Organization"}, "topics": ["biological-expression-language", "ontologies", "terminologies"], "timestamp": "2022-07-20 17:29:43.481805", "avatar": "https://avatars.githubusercontent.com/u/22892058?v=4"}}
