{"parser": "github", "uid": "github/spyder-ide/spyder", "url": "https://github.com/spyder-ide/spyder", "data": {"timestamp": "2020-06-09 13:28:53.034921", "id": 30892477, "node_id": "MDEwOlJlcG9zaXRvcnkzMDg5MjQ3Nw==", "name": "spyder", "full_name": "spyder-ide/spyder", "private": false, "owner": {"login": "spyder-ide", "id": 1284937, "node_id": "MDEyOk9yZ2FuaXphdGlvbjEyODQ5Mzc=", "avatar_url": "https://avatars1.githubusercontent.com/u/1284937?v=4", "gravatar_id": "", "url": "https://api.github.com/users/spyder-ide", "html_url": "https://github.com/spyder-ide", "followers_url": "https://api.github.com/users/spyder-ide/followers", "following_url": "https://api.github.com/users/spyder-ide/following{/other_user}", "gists_url": "https://api.github.com/users/spyder-ide/gists{/gist_id}", "starred_url": "https://api.github.com/users/spyder-ide/starred{/owner}{/repo}", "subscriptions_url": "https://api.github.com/users/spyder-ide/subscriptions", "organizations_url": "https://api.github.com/users/spyder-ide/orgs", "repos_url": "https://api.github.com/users/spyder-ide/repos", "events_url": "https://api.github.com/users/spyder-ide/events{/privacy}", "received_events_url": "https://api.github.com/users/spyder-ide/received_events", "type": "Organization", "site_admin": false}, "html_url": "https://github.com/spyder-ide/spyder", "description": "Official repository for Spyder - The Scientific Python Development Environment", "fork": false, "url": "https://api.github.com/repos/spyder-ide/spyder", "forks_url": "https://api.github.com/repos/spyder-ide/spyder/forks", "keys_url": "https://api.github.com/repos/spyder-ide/spyder/keys{/key_id}", "collaborators_url": "https://api.github.com/repos/spyder-ide/spyder/collaborators{/collaborator}", "teams_url": "https://api.github.com/repos/spyder-ide/spyder/teams", "hooks_url": "https://api.github.com/repos/spyder-ide/spyder/hooks", "issue_events_url": "https://api.github.com/repos/spyder-ide/spyder/issues/events{/number}", "events_url": "https://api.github.com/repos/spyder-ide/spyder/events", "assignees_url": "https://api.github.com/repos/spyder-ide/spyder/assignees{/user}", "branches_url": "https://api.github.com/repos/spyder-ide/spyder/branches{/branch}", "tags_url": "https://api.github.com/repos/spyder-ide/spyder/tags", "blobs_url": "https://api.github.com/repos/spyder-ide/spyder/git/blobs{/sha}", "git_tags_url": "https://api.github.com/repos/spyder-ide/spyder/git/tags{/sha}", "git_refs_url": "https://api.github.com/repos/spyder-ide/spyder/git/refs{/sha}", "trees_url": "https://api.github.com/repos/spyder-ide/spyder/git/trees{/sha}", "statuses_url": "https://api.github.com/repos/spyder-ide/spyder/statuses/{sha}", "languages_url": "https://api.github.com/repos/spyder-ide/spyder/languages", "stargazers_url": "https://api.github.com/repos/spyder-ide/spyder/stargazers", "contributors_url": "https://api.github.com/repos/spyder-ide/spyder/contributors", "subscribers_url": "https://api.github.com/repos/spyder-ide/spyder/subscribers", "subscription_url": "https://api.github.com/repos/spyder-ide/spyder/subscription", "commits_url": "https://api.github.com/repos/spyder-ide/spyder/commits{/sha}", "git_commits_url": "https://api.github.com/repos/spyder-ide/spyder/git/commits{/sha}", "comments_url": "https://api.github.com/repos/spyder-ide/spyder/comments{/number}", "issue_comment_url": "https://api.github.com/repos/spyder-ide/spyder/issues/comments{/number}", "contents_url": "https://api.github.com/repos/spyder-ide/spyder/contents/{+path}", "compare_url": "https://api.github.com/repos/spyder-ide/spyder/compare/{base}...{head}", "merges_url": "https://api.github.com/repos/spyder-ide/spyder/merges", "archive_url": "https://api.github.com/repos/spyder-ide/spyder/{archive_format}{/ref}", "downloads_url": "https://api.github.com/repos/spyder-ide/spyder/downloads", "issues_url": "https://api.github.com/repos/spyder-ide/spyder/issues{/number}", "pulls_url": "https://api.github.com/repos/spyder-ide/spyder/pulls{/number}", "milestones_url": "https://api.github.com/repos/spyder-ide/spyder/milestones{/number}", "notifications_url": "https://api.github.com/repos/spyder-ide/spyder/notifications{?since,all,participating}", "labels_url": "https://api.github.com/repos/spyder-ide/spyder/labels{/name}", "releases_url": "https://api.github.com/repos/spyder-ide/spyder/releases{/id}", "deployments_url": "https://api.github.com/repos/spyder-ide/spyder/deployments", "created_at": "2015-02-16T22:49:48Z", "updated_at": "2020-06-09T06:40:48Z", "pushed_at": "2020-06-09T03:04:27Z", "git_url": "git://github.com/spyder-ide/spyder.git", "ssh_url": "git@github.com:spyder-ide/spyder.git", "clone_url": "https://github.com/spyder-ide/spyder.git", "svn_url": "https://github.com/spyder-ide/spyder", "homepage": "https://www.spyder-ide.org/", "size": 73954, "stargazers_count": 5461, "watchers_count": 5461, "language": "Python", "has_issues": true, "has_projects": true, "has_downloads": true, "has_wiki": true, "has_pages": false, "forks_count": 1102, "mirror_url": null, "archived": false, "disabled": false, "open_issues_count": 884, "license": {"key": "mit", "name": "MIT License", "spdx_id": "MIT", "url": "https://api.github.com/licenses/mit", "node_id": "MDc6TGljZW5zZTEz"}, "forks": 1102, "open_issues": 884, "watchers": 5461, "default_branch": "master", "permissions": {"admin": false, "push": false, "pull": true}, "temp_clone_token": "", "organization": {"login": "spyder-ide", "id": 1284937, "node_id": "MDEyOk9yZ2FuaXphdGlvbjEyODQ5Mzc=", "avatar_url": "https://avatars1.githubusercontent.com/u/1284937?v=4", "gravatar_id": "", "url": "https://api.github.com/users/spyder-ide", "html_url": "https://github.com/spyder-ide", "followers_url": "https://api.github.com/users/spyder-ide/followers", "following_url": "https://api.github.com/users/spyder-ide/following{/other_user}", "gists_url": "https://api.github.com/users/spyder-ide/gists{/gist_id}", "starred_url": "https://api.github.com/users/spyder-ide/starred{/owner}{/repo}", "subscriptions_url": "https://api.github.com/users/spyder-ide/subscriptions", "organizations_url": "https://api.github.com/users/spyder-ide/orgs", "repos_url": "https://api.github.com/users/spyder-ide/repos", "events_url": "https://api.github.com/users/spyder-ide/events{/privacy}", "received_events_url": "https://api.github.com/users/spyder-ide/received_events", "type": "Organization", "site_admin": false}, "network_count": 1102, "subscribers_count": 284}}
