{"parser": "github", "uid": "github/natashabatalha/picaso", "url": "https://github.com/natashabatalha/picaso", "data": {"doi": ["https://ui.adsabs.harvard.edu/abs/2019arXiv190409355B", "https://ui.adsabs.harvard.edu/abs/2019ascl.soft05019B/abstract"], "title": "PICASO: Planetary Intensity Code for Atmospheric Scattering Observations", "url": "https://github.com/natashabatalha/picaso", "name": "picaso", "full_name": "natashabatalha/picaso", "html_url": "https://github.com/natashabatalha/picaso", "description": "A Planetary Intensity Code for Atmospheric Spectroscopy Observations", "created_at": "2017-12-07T16:34:06Z", "updated_at": "2022-05-31T19:25:03Z", "clone_url": "https://github.com/natashabatalha/picaso.git", "homepage": "https://natashabatalha.github.io/picaso", "size": 572395, "stargazers_count": 25, "watchers_count": 25, "language": "Python", "open_issues_count": 5, "license": {"key": "gpl-3.0", "name": "GNU General Public License v3.0", "spdx_id": "GPL-3.0", "url": "https://api.github.com/licenses/gpl-3.0", "node_id": "MDc6TGljZW5zZTk="}, "subscribers_count": 6, "owner": {"html_url": "https://github.com/natashabatalha", "avatar_url": "https://avatars.githubusercontent.com/u/6554465?v=4", "login": "natashabatalha", "type": "User"}, "topics": ["exoplanets", "atmospheric-science", "planetary-science", "scattering", "atmospheres", "direct-imaging", "transmission", "emission", "reflected-light"], "timestamp": "2022-07-17 17:16:44.038529", "avatar": "https://avatars.githubusercontent.com/u/6554465?v=4"}}
