{"parser": "github", "uid": "github/optimusmoose/jsms", "url": "https://github.com/optimusmoose/jsms", "data": {"timestamp": "2021-01-17 00:54:48.565077", "name": "jsms", "url": "https://api.github.com/repos/optimusmoose/jsms", "full_name": "optimusmoose/jsms", "html_url": "https://github.com/optimusmoose/jsms", "private": false, "description": "A modular JavaScript viewer for mass spectrometry data", "created_at": "2017-01-17T22:54:08Z", "updated_at": "2020-10-01T15:26:00Z", "clone_url": "https://github.com/optimusmoose/jsms.git", "homepage": null, "size": 99650, "stargazers_count": 9, "watchers_count": 9, "language": "Java", "open_issues_count": 2, "license": null, "subscribers_count": 4, "owner": {"html_url": "https://github.com/optimusmoose", "avatar_url": "https://avatars2.githubusercontent.com/u/1541778?v=4", "login": "optimusmoose", "type": "User"}, "topics": []}, "doi": "10.1101/2019.12.27.889253"}
