{"parser": "github", "uid": "github/pybop-team/PyBOP", "url": "https://github.com/pybop-team/PyBOP", "data": {"doi": "https://doi.org/10.5281/zenodo.17711656", "name": "PyBOP", "url": "https://github.com/pybop-team/PyBOP", "full_name": "pybop-team/PyBOP", "html_url": "https://github.com/pybop-team/PyBOP", "description": "A parameterisation and optimisation package for battery models.", "created_at": "2023-06-13T10:44:32Z", "updated_at": "2025-12-05T21:14:58Z", "clone_url": "https://github.com/pybop-team/PyBOP.git", "homepage": "https://pybop-docs.readthedocs.io", "size": 87363, "stargazers_count": 162, "watchers_count": 162, "language": "Python", "open_issues_count": 62, "license": {"key": "bsd-3-clause", "name": "BSD 3-Clause \"New\" or \"Revised\" License", "spdx_id": "BSD-3-Clause", "url": "https://api.github.com/licenses/bsd-3-clause", "node_id": "MDc6TGljZW5zZTU="}, "subscribers_count": 4, "owner": {"html_url": "https://github.com/pybop-team", "avatar_url": "https://avatars.githubusercontent.com/u/136452226?v=4", "login": "pybop-team", "type": "Organization"}, "timestamp": "2025-12-07 00:58:57.673157", "avatar": "https://avatars.githubusercontent.com/u/136452226?v=4"}}
