{"parser": "github", "uid": "github/hombit/freddi", "url": "https://github.com/hombit/freddi", "data": {"doi": ["https://ui.adsabs.harvard.edu/abs/2017MNRAS.468.4735L", "https://ui.adsabs.harvard.edu/abs/2016ascl.soft10014M/abstract"], "title": "Freddi: Fast Rise Exponential Decay accretion Disk model Implementation", "url": "https://github.com/hombit/freddi", "name": "freddi", "full_name": "hombit/freddi", "html_url": "https://github.com/hombit/freddi", "description": "Compute FRED light curves of LMXBs outbursts", "created_at": "2015-12-23T09:10:25Z", "updated_at": "2022-02-19T07:32:47Z", "clone_url": "https://github.com/hombit/freddi.git", "homepage": "http://freddi.homb.it", "size": 2039, "stargazers_count": 6, "watchers_count": 6, "language": "C++", "open_issues_count": 9, "subscribers_count": 4, "owner": {"html_url": "https://github.com/hombit", "avatar_url": "https://avatars.githubusercontent.com/u/1784493?v=4", "login": "hombit", "type": "User"}, "topics": ["accretion-disks", "astrophysics", "x-ray-binaries", "fred", "science", "lmxb"], "timestamp": "2022-07-17 17:21:07.761934", "avatar": "https://avatars.githubusercontent.com/u/1784493?v=4"}}
