{
    "parser": "github",
    "uid": "github/henry2004y/Vlasiator.jl",
    "url": "https://github.com/henry2004y/Vlasiator.jl",
    "data": {
        "doi": "https://doi.org/10.5281/zenodo.7769707",
        "name": "Vlasiator.jl",
        "url": "https://github.com/henry2004y/Vlasiator.jl",
        "full_name": "henry2004y/Vlasiator.jl",
        "html_url": "https://github.com/henry2004y/Vlasiator.jl",
        "description": "Data processor for Vlasiator",
        "created_at": "2021-01-23T19:59:54Z",
        "updated_at": "2023-01-31T18:42:19Z",
        "clone_url": "https://github.com/henry2004y/Vlasiator.jl.git",
        "homepage": "https://henry2004y.github.io/Vlasiator.jl/stable/",
        "size": 11160,
        "stargazers_count": 6,
        "watchers_count": 6,
        "language": "Julia",
        "open_issues_count": 19,
        "license": {
            "key": "mit",
            "name": "MIT License",
            "spdx_id": "MIT",
            "url": "https://api.github.com/licenses/mit",
            "node_id": "MDc6TGljZW5zZTEz"
        },
        "subscribers_count": 2,
        "owner": {
            "html_url": "https://github.com/henry2004y",
            "avatar_url": "https://avatars.githubusercontent.com/u/20110816?v=4",
            "login": "henry2004y",
            "type": "User"
        },
        "timestamp": "2023-04-09 00:35:19.595137",
        "avatar": "https://avatars.githubusercontent.com/u/20110816?v=4"
    }
}