{
    "parser": "github",
    "uid": "github/vimc/orderly",
    "url": "https://github.com/vimc/orderly",
    "data": {
        "timestamp": "2022-05-12 03:44:00.062153",
        "name": "orderly",
        "url": "https://api.github.com/repos/vimc/orderly",
        "full_name": "vimc/orderly",
        "html_url": "https://github.com/vimc/orderly",
        "private": false,
        "description": ":hospital::ambulance: Lightweight Reproducible Reporting for R",
        "created_at": "2017-05-22T10:58:56Z",
        "updated_at": "2022-05-06T06:09:42Z",
        "clone_url": "https://github.com/vimc/orderly.git",
        "homepage": "https://www.vaccineimpact.org/orderly/",
        "size": 13356,
        "stargazers_count": 101,
        "watchers_count": 101,
        "language": "R",
        "open_issues_count": 12,
        "license": {
            "key": "other",
            "name": "Other",
            "spdx_id": "NOASSERTION",
            "url": null,
            "node_id": "MDc6TGljZW5zZTA="
        },
        "subscribers_count": 4,
        "owner": {
            "html_url": "https://github.com/vimc",
            "avatar_url": "https://avatars.githubusercontent.com/u/26278316?v=4",
            "login": "vimc",
            "type": "Organization"
        },
        "topics": []
    },
    "rsotm": "2019-02"
}