{"parser": "github", "uid": "github/weber1158/eds-classification", "url": "https://github.com/weber1158/eds-classification", "data": {"doi": "https://doi.org/10.5281/zenodo.14989511", "name": "eds-classification", "url": "https://github.com/weber1158/eds-classification", "full_name": "weber1158/eds-classification", "html_url": "https://github.com/weber1158/eds-classification", "description": "Functions for working with SEM-EDS data in MATLAB, including different algorithms for performing mineral classification.", "created_at": "2024-05-20T14:32:19Z", "updated_at": "2025-03-10T19:31:57Z", "clone_url": "https://github.com/weber1158/eds-classification.git", "size": 10178, "language": "MATLAB", "license": {"key": "mit", "name": "MIT License", "spdx_id": "MIT", "url": "https://api.github.com/licenses/mit", "node_id": "MDc6TGljZW5zZTEz"}, "subscribers_count": 1, "owner": {"html_url": "https://github.com/weber1158", "avatar_url": "https://avatars.githubusercontent.com/u/133900499?v=4", "login": "weber1158", "type": "User"}, "timestamp": "2025-03-16 00:49:56.856388", "avatar": "https://avatars.githubusercontent.com/u/133900499?v=4"}}
