{"parser": "github", "uid": "github/ropensci/rvertnet", "url": "https://github.com/ropensci/rvertnet", "data": {"timestamp": "2022-01-27 10:11:35.067594", "name": "rvertnet", "url": "https://api.github.com/repos/ropensci/rvertnet", "full_name": "ropensci/rvertnet", "html_url": "https://github.com/ropensci/rvertnet", "private": false, "description": "Wrapper to the VertNet API", "created_at": "2011-09-09T16:30:41Z", "updated_at": "2021-07-16T15:33:20Z", "clone_url": "https://github.com/ropensci/rvertnet.git", "homepage": "https://docs.ropensci.org/rvertnet", "size": 1665, "stargazers_count": 4, "watchers_count": 4, "language": "R", "open_issues_count": 1, "license": {"key": "other", "name": "Other", "spdx_id": "NOASSERTION", "url": null, "node_id": "MDc6TGljZW5zZTA="}, "owner": {"html_url": "https://github.com/ropensci", "avatar_url": "https://avatars.githubusercontent.com/u/1200269?v=4", "login": "ropensci", "type": "Organization"}, "topics": ["api-wrapper", "biodiversity", "specimen", "rstats", "vertnet", "r", "spocc", "r-package", "mammalia", "mammals", "maps", "occurrences", "species", "specimens", "data-access"]}}
