{"parser": "github", "uid": "github/entangled/entangled", "url": "https://api.github.com/repos/entangled/entangled", "data": {"timestamp": "2020-07-05 00:17:27.043027", "name": "entangled", "url": "https://api.github.com/repos/entangled/entangled", "full_name": "entangled/entangled", "html_url": "https://github.com/entangled/entangled", "private": false, "description": "bi-directional tangle daemon for literate programming", "created_at": "2018-12-07T15:37:48Z", "updated_at": "2020-06-21T23:02:30Z", "clone_url": "https://github.com/entangled/entangled.git", "homepage": "https://entangled.github.io/", "size": 5517, "stargazers_count": 16, "watchers_count": 16, "language": "Haskell", "open_issues_count": 7, "license": {"key": "apache-2.0", "name": "Apache License 2.0", "spdx_id": "Apache-2.0", "url": "https://api.github.com/licenses/apache-2.0", "node_id": "MDc6TGljZW5zZTI="}, "subscribers_count": 4, "owner": {"html_url": "https://github.com/entangled", "avatar_url": "https://avatars2.githubusercontent.com/u/58023578?v=4", "login": "entangled", "type": "Organization"}}, "doi": "10.5281/zenodo.3877116", "name": "entangled", "full_name": "entangled/entangled", "html_url": "https://github.com/entangled/entangled", "private": false, "description": "bi-directional tangle daemon for literate programming", "created_at": "2018-12-07T15:37:48Z", "updated_at": "2020-07-17T19:13:09Z", "clone_url": "https://github.com/entangled/entangled.git", "homepage": "https://entangled.github.io/", "size": 5517, "stargazers_count": 18, "watchers_count": 18, "language": "Haskell", "open_issues_count": 9, "license": {"key": "apache-2.0", "name": "Apache License 2.0", "spdx_id": "Apache-2.0", "url": "https://api.github.com/licenses/apache-2.0", "node_id": "MDc6TGljZW5zZTI="}, "subscribers_count": 4, "owner": {"html_url": "https://github.com/entangled", "avatar_url": "https://avatars2.githubusercontent.com/u/58023578?v=4", "login": "entangled", "type": "Organization"}, "topics": []}
