{"parser": "github", "uid": "github/mrvollger/fibertools-rs", "url": "https://github.com/mrvollger/fibertools-rs", "data": {"title": "fibertools\u2011rs", "url": "https://github.com/mrvollger/fibertools-rs", "credit": [], "tags": ["high-throughput-sequencing"], "description": "Tools for fiberseq data written in rust. ", "name": "fibertools-rs", "full_name": "mrvollger/fibertools-rs", "html_url": "https://github.com/mrvollger/fibertools-rs", "created_at": "2022-07-24T13:57:47Z", "updated_at": "2022-11-21T23:27:08Z", "clone_url": "https://github.com/mrvollger/fibertools-rs.git", "homepage": "https://mrvollger.github.io/fibertools-rs/", "size": 94370, "stargazers_count": 4, "watchers_count": 4, "language": "Rust", "subscribers_count": 2, "owner": {"html_url": "https://github.com/mrvollger", "avatar_url": "https://avatars.githubusercontent.com/u/6935283?v=4", "login": "mrvollger", "type": "User"}, "timestamp": "2022-11-27 00:42:35.979054", "avatar": "https://avatars.githubusercontent.com/u/6935283?v=4"}}
