{"parser": "github", "uid": "github/MichielsenM/FOAM", "url": "https://github.com/MichielsenM/FOAM", "data": {"doi": "https://doi.org/10.5281/zenodo.11237626", "name": "FOAM", "url": "https://github.com/MichielsenM/FOAM", "full_name": "MichielsenM/FOAM", "html_url": "https://github.com/MichielsenM/FOAM", "description": "A Python package for forward asteroseismic modelling of gravity modes", "created_at": "2019-10-08T16:31:39Z", "updated_at": "2024-05-28T17:09:18Z", "clone_url": "https://github.com/MichielsenM/FOAM.git", "homepage": "https://michielsenm.github.io/FOAM/", "size": 66990, "stargazers_count": 4, "watchers_count": 4, "language": "Python", "open_issues_count": 2, "license": {"key": "gpl-3.0", "name": "GNU General Public License v3.0", "spdx_id": "GPL-3.0", "url": "https://api.github.com/licenses/gpl-3.0", "node_id": "MDc6TGljZW5zZTk="}, "subscribers_count": 1, "owner": {"html_url": "https://github.com/MichielsenM", "avatar_url": "https://avatars.githubusercontent.com/u/33225623?v=4", "login": "MichielsenM", "type": "User"}, "topics": ["asteroseismology", "astronomy", "python", "astrophysics"], "timestamp": "2024-06-02 00:38:06.502624", "avatar": "https://avatars.githubusercontent.com/u/33225623?v=4"}}
