{"parser": "github", "uid": "github/ImperialCollegeLondon/PyProBE", "url": "https://github.com/ImperialCollegeLondon/PyProBE", "data": {"doi": "https://doi.org/10.5281/zenodo.14796110", "name": "PyProBE", "url": "https://github.com/ImperialCollegeLondon/PyProBE", "full_name": "ImperialCollegeLondon/PyProBE", "html_url": "https://github.com/ImperialCollegeLondon/PyProBE", "description": "Python Processing for Battery Experiments", "created_at": "2024-05-15T16:36:54Z", "updated_at": "2025-02-12T16:17:38Z", "clone_url": "https://github.com/ImperialCollegeLondon/PyProBE.git", "homepage": "https://imperialcollegelondon.github.io/PyProBE/", "size": 265979, "stargazers_count": 17, "watchers_count": 17, "language": "Python", "open_issues_count": 14, "license": {"key": "bsd-3-clause", "name": "BSD 3-Clause \"New\" or \"Revised\" License", "spdx_id": "BSD-3-Clause", "url": "https://api.github.com/licenses/bsd-3-clause", "node_id": "MDc6TGljZW5zZTU="}, "subscribers_count": 2, "owner": {"html_url": "https://github.com/ImperialCollegeLondon", "avatar_url": "https://avatars.githubusercontent.com/u/1220306?v=4", "login": "ImperialCollegeLondon", "type": "Organization"}, "timestamp": "2025-02-16 00:47:18.246462", "avatar": "https://avatars.githubusercontent.com/u/1220306?v=4"}}
