{
    "parser": "github",
    "uid": "github/ConnorStoneAstro/AutoProf",
    "url": "https://github.com/ConnorStoneAstro/AutoProf",
    "data": {
        "doi": [
            "https://ui.adsabs.harvard.edu/abs/2021arXiv210613809S",
            "https://ui.adsabs.harvard.edu/abs/2021ascl.soft08017S/abstract"
        ],
        "title": "AutoProf: Automatic Isophotal solutions for galaxy images",
        "url": "https://github.com/ConnorStoneAstro/AutoProf",
        "name": "AutoProf",
        "full_name": "ConnorStoneAstro/AutoProf",
        "html_url": "https://github.com/ConnorStoneAstro/AutoProf",
        "description": "Automatic Isophotal solutions for galaxy images",
        "created_at": "2021-02-04T16:37:40Z",
        "updated_at": "2022-05-22T22:25:00Z",
        "clone_url": "https://github.com/ConnorStoneAstro/AutoProf.git",
        "size": 49684,
        "stargazers_count": 22,
        "watchers_count": 22,
        "language": "Python",
        "license": {
            "key": "gpl-3.0",
            "name": "GNU General Public License v3.0",
            "spdx_id": "GPL-3.0",
            "url": "https://api.github.com/licenses/gpl-3.0",
            "node_id": "MDc6TGljZW5zZTk="
        },
        "subscribers_count": 2,
        "owner": {
            "html_url": "https://github.com/ConnorStoneAstro",
            "avatar_url": "https://avatars.githubusercontent.com/u/78555321?v=4",
            "login": "ConnorStoneAstro",
            "type": "User"
        },
        "timestamp": "2022-07-17 17:11:09.463627",
        "avatar": "https://avatars.githubusercontent.com/u/78555321?v=4"
    }
}