{
    "parser": "github",
    "uid": "github/CrowdTruth/CrowdTruth",
    "url": "https://github.com/CrowdTruth/CrowdTruth",
    "data": {
        "timestamp": "2020-06-28 08:44:59.095917",
        "id": 19739006,
        "node_id": "MDEwOlJlcG9zaXRvcnkxOTczOTAwNg==",
        "name": "CrowdTruth",
        "full_name": "CrowdTruth/CrowdTruth",
        "private": false,
        "owner": {
            "login": "CrowdTruth",
            "id": 8793398,
            "node_id": "MDEyOk9yZ2FuaXphdGlvbjg3OTMzOTg=",
            "avatar_url": "https://avatars3.githubusercontent.com/u/8793398?v=4",
            "gravatar_id": "",
            "url": "https://api.github.com/users/CrowdTruth",
            "html_url": "https://github.com/CrowdTruth",
            "followers_url": "https://api.github.com/users/CrowdTruth/followers",
            "following_url": "https://api.github.com/users/CrowdTruth/following{/other_user}",
            "gists_url": "https://api.github.com/users/CrowdTruth/gists{/gist_id}",
            "starred_url": "https://api.github.com/users/CrowdTruth/starred{/owner}{/repo}",
            "subscriptions_url": "https://api.github.com/users/CrowdTruth/subscriptions",
            "organizations_url": "https://api.github.com/users/CrowdTruth/orgs",
            "repos_url": "https://api.github.com/users/CrowdTruth/repos",
            "events_url": "https://api.github.com/users/CrowdTruth/events{/privacy}",
            "received_events_url": "https://api.github.com/users/CrowdTruth/received_events",
            "type": "Organization",
            "site_admin": false
        },
        "html_url": "https://github.com/CrowdTruth/CrowdTruth",
        "description": "Version 1.0 of the CrowdTruth Framework for crowdsourcing ground truth data, for training and evaluation of cognitive computing systems. Check out also version 2.0 at https://github.com/CrowdTruth/CrowdTruth-core. Data collected with CrowdTruth methodology: http://data.crowdtruth.org/. Our papers: http://crowdtruth.org/papers/",
        "fork": false,
        "url": "https://api.github.com/repos/CrowdTruth/CrowdTruth",
        "forks_url": "https://api.github.com/repos/CrowdTruth/CrowdTruth/forks",
        "keys_url": "https://api.github.com/repos/CrowdTruth/CrowdTruth/keys{/key_id}",
        "collaborators_url": "https://api.github.com/repos/CrowdTruth/CrowdTruth/collaborators{/collaborator}",
        "teams_url": "https://api.github.com/repos/CrowdTruth/CrowdTruth/teams",
        "hooks_url": "https://api.github.com/repos/CrowdTruth/CrowdTruth/hooks",
        "issue_events_url": "https://api.github.com/repos/CrowdTruth/CrowdTruth/issues/events{/number}",
        "events_url": "https://api.github.com/repos/CrowdTruth/CrowdTruth/events",
        "assignees_url": "https://api.github.com/repos/CrowdTruth/CrowdTruth/assignees{/user}",
        "branches_url": "https://api.github.com/repos/CrowdTruth/CrowdTruth/branches{/branch}",
        "tags_url": "https://api.github.com/repos/CrowdTruth/CrowdTruth/tags",
        "blobs_url": "https://api.github.com/repos/CrowdTruth/CrowdTruth/git/blobs{/sha}",
        "git_tags_url": "https://api.github.com/repos/CrowdTruth/CrowdTruth/git/tags{/sha}",
        "git_refs_url": "https://api.github.com/repos/CrowdTruth/CrowdTruth/git/refs{/sha}",
        "trees_url": "https://api.github.com/repos/CrowdTruth/CrowdTruth/git/trees{/sha}",
        "statuses_url": "https://api.github.com/repos/CrowdTruth/CrowdTruth/statuses/{sha}",
        "languages_url": "https://api.github.com/repos/CrowdTruth/CrowdTruth/languages",
        "stargazers_url": "https://api.github.com/repos/CrowdTruth/CrowdTruth/stargazers",
        "contributors_url": "https://api.github.com/repos/CrowdTruth/CrowdTruth/contributors",
        "subscribers_url": "https://api.github.com/repos/CrowdTruth/CrowdTruth/subscribers",
        "subscription_url": "https://api.github.com/repos/CrowdTruth/CrowdTruth/subscription",
        "commits_url": "https://api.github.com/repos/CrowdTruth/CrowdTruth/commits{/sha}",
        "git_commits_url": "https://api.github.com/repos/CrowdTruth/CrowdTruth/git/commits{/sha}",
        "comments_url": "https://api.github.com/repos/CrowdTruth/CrowdTruth/comments{/number}",
        "issue_comment_url": "https://api.github.com/repos/CrowdTruth/CrowdTruth/issues/comments{/number}",
        "contents_url": "https://api.github.com/repos/CrowdTruth/CrowdTruth/contents/{+path}",
        "compare_url": "https://api.github.com/repos/CrowdTruth/CrowdTruth/compare/{base}...{head}",
        "merges_url": "https://api.github.com/repos/CrowdTruth/CrowdTruth/merges",
        "archive_url": "https://api.github.com/repos/CrowdTruth/CrowdTruth/{archive_format}{/ref}",
        "downloads_url": "https://api.github.com/repos/CrowdTruth/CrowdTruth/downloads",
        "issues_url": "https://api.github.com/repos/CrowdTruth/CrowdTruth/issues{/number}",
        "pulls_url": "https://api.github.com/repos/CrowdTruth/CrowdTruth/pulls{/number}",
        "milestones_url": "https://api.github.com/repos/CrowdTruth/CrowdTruth/milestones{/number}",
        "notifications_url": "https://api.github.com/repos/CrowdTruth/CrowdTruth/notifications{?since,all,participating}",
        "labels_url": "https://api.github.com/repos/CrowdTruth/CrowdTruth/labels{/name}",
        "releases_url": "https://api.github.com/repos/CrowdTruth/CrowdTruth/releases{/id}",
        "deployments_url": "https://api.github.com/repos/CrowdTruth/CrowdTruth/deployments",
        "created_at": "2014-05-13T12:56:25Z",
        "updated_at": "2020-01-20T11:46:10Z",
        "pushed_at": "2018-08-30T12:25:50Z",
        "git_url": "git://github.com/CrowdTruth/CrowdTruth.git",
        "ssh_url": "git@github.com:CrowdTruth/CrowdTruth.git",
        "clone_url": "https://github.com/CrowdTruth/CrowdTruth.git",
        "svn_url": "https://github.com/CrowdTruth/CrowdTruth",
        "homepage": "http://crowdtruth.org",
        "size": 103661,
        "stargazers_count": 60,
        "watchers_count": 60,
        "language": "JavaScript",
        "has_issues": true,
        "has_projects": true,
        "has_downloads": true,
        "has_wiki": true,
        "has_pages": false,
        "forks_count": 16,
        "mirror_url": null,
        "archived": false,
        "disabled": false,
        "open_issues_count": 33,
        "license": null,
        "forks": 16,
        "open_issues": 33,
        "watchers": 60,
        "default_branch": "dev",
        "permissions": {
            "admin": false,
            "push": false,
            "pull": false
        },
        "temp_clone_token": "",
        "organization": {
            "login": "CrowdTruth",
            "id": 8793398,
            "node_id": "MDEyOk9yZ2FuaXphdGlvbjg3OTMzOTg=",
            "avatar_url": "https://avatars3.githubusercontent.com/u/8793398?v=4",
            "gravatar_id": "",
            "url": "https://api.github.com/users/CrowdTruth",
            "html_url": "https://github.com/CrowdTruth",
            "followers_url": "https://api.github.com/users/CrowdTruth/followers",
            "following_url": "https://api.github.com/users/CrowdTruth/following{/other_user}",
            "gists_url": "https://api.github.com/users/CrowdTruth/gists{/gist_id}",
            "starred_url": "https://api.github.com/users/CrowdTruth/starred{/owner}{/repo}",
            "subscriptions_url": "https://api.github.com/users/CrowdTruth/subscriptions",
            "organizations_url": "https://api.github.com/users/CrowdTruth/orgs",
            "repos_url": "https://api.github.com/users/CrowdTruth/repos",
            "events_url": "https://api.github.com/users/CrowdTruth/events{/privacy}",
            "received_events_url": "https://api.github.com/users/CrowdTruth/received_events",
            "type": "Organization",
            "site_admin": false
        },
        "network_count": 16,
        "subscribers_count": 18
    }
}