{
    "parser": "github",
    "uid": "github/glencoesoftware/raw2ometiff",
    "url": "https://github.com/glencoesoftware/raw2ometiff",
    "data": {
        "name": "raw2ometiff",
        "url": "https://github.com/glencoesoftware/raw2ometiff",
        "full_name": "glencoesoftware/raw2ometiff",
        "html_url": "https://github.com/glencoesoftware/raw2ometiff",
        "private": false,
        "description": "Raw format to OME-TIFF converter",
        "created_at": "2019-10-09T14:50:58Z",
        "updated_at": "2025-10-01T10:31:06Z",
        "clone_url": "https://github.com/glencoesoftware/raw2ometiff.git",
        "homepage": null,
        "size": 542,
        "stargazers_count": 56,
        "watchers_count": 56,
        "language": "Java",
        "open_issues_count": 6,
        "license": {
            "key": "gpl-2.0",
            "name": "GNU General Public License v2.0",
            "spdx_id": "GPL-2.0",
            "url": "https://api.github.com/licenses/gpl-2.0",
            "node_id": "MDc6TGljZW5zZTg="
        },
        "subscribers_count": 15,
        "owner": {
            "html_url": "https://github.com/glencoesoftware",
            "avatar_url": "https://avatars.githubusercontent.com/u/1376006?v=4",
            "login": "glencoesoftware",
            "type": "Organization"
        },
        "topics": [],
        "timestamp": "2025-11-02 00:54:40.424922",
        "avatar": "https://avatars.githubusercontent.com/u/1376006?v=4"
    }
}