{"parser": "github", "uid": "github/iomega/spec2vec", "url": "https://api.github.com/repos/iomega/spec2vec", "data": {"timestamp": "2020-07-05 00:17:29.461435", "name": "spec2vec", "url": "https://api.github.com/repos/iomega/spec2vec", "full_name": "iomega/spec2vec", "html_url": "https://github.com/iomega/spec2vec", "private": false, "description": "Word2Vec based similarity measure of mass spectrometry data.", "created_at": "2020-05-13T13:35:33Z", "updated_at": "2020-06-25T12:50:31Z", "clone_url": "https://github.com/iomega/spec2vec.git", "homepage": null, "size": 21991, "stargazers_count": 0, "watchers_count": 0, "language": "Python", "open_issues_count": 5, "license": {"key": "apache-2.0", "name": "Apache License 2.0", "spdx_id": "Apache-2.0", "url": "https://api.github.com/licenses/apache-2.0", "node_id": "MDc6TGljZW5zZTI="}, "subscribers_count": 6, "owner": {"html_url": "https://github.com/iomega", "avatar_url": "https://avatars3.githubusercontent.com/u/39822447?v=4", "login": "iomega", "type": "Organization"}}, "name": "spec2vec", "full_name": "iomega/spec2vec", "html_url": "https://github.com/iomega/spec2vec", "private": false, "description": "Word2Vec based similarity measure of mass spectrometry data.", "created_at": "2020-05-13T13:35:33Z", "updated_at": "2020-08-18T23:43:14Z", "clone_url": "https://github.com/iomega/spec2vec.git", "homepage": null, "size": 22030, "stargazers_count": 2, "watchers_count": 2, "language": "Python", "open_issues_count": 6, "license": {"key": "apache-2.0", "name": "Apache License 2.0", "spdx_id": "Apache-2.0", "url": "https://api.github.com/licenses/apache-2.0", "node_id": "MDc6TGljZW5zZTI="}, "subscribers_count": 5, "owner": {"html_url": "https://github.com/iomega", "avatar_url": "https://avatars3.githubusercontent.com/u/39822447?v=4", "login": "iomega", "type": "Organization"}, "topics": ["word2vec", "mass-spectrometry", "fuzzy-matching", "fuzzy-search"]}
