{
    "parser": "github",
    "uid": "github/glencoesoftware/bioformats2raw",
    "url": "https://github.com/glencoesoftware/bioformats2raw",
    "data": {
        "name": "bioformats2raw",
        "url": "https://github.com/glencoesoftware/bioformats2raw",
        "full_name": "glencoesoftware/bioformats2raw",
        "html_url": "https://github.com/glencoesoftware/bioformats2raw",
        "private": false,
        "description": "Bio-Formats image file format to raw format converter",
        "created_at": "2019-10-09T14:47:33Z",
        "updated_at": "2025-10-23T09:07:58Z",
        "clone_url": "https://github.com/glencoesoftware/bioformats2raw.git",
        "homepage": "",
        "size": 1238,
        "stargazers_count": 99,
        "watchers_count": 99,
        "language": "Java",
        "open_issues_count": 19,
        "license": {
            "key": "gpl-2.0",
            "name": "GNU General Public License v2.0",
            "spdx_id": "GPL-2.0",
            "url": "https://api.github.com/licenses/gpl-2.0",
            "node_id": "MDc6TGljZW5zZTg="
        },
        "subscribers_count": 16,
        "owner": {
            "html_url": "https://github.com/glencoesoftware",
            "avatar_url": "https://avatars.githubusercontent.com/u/1376006?v=4",
            "login": "glencoesoftware",
            "type": "Organization"
        },
        "topics": [
            "ome-zarr-converter"
        ],
        "timestamp": "2025-10-26 00:53:23.898123",
        "avatar": "https://avatars.githubusercontent.com/u/1376006?v=4"
    }
}