{
    "parser": "github",
    "uid": "github/nhcrisp/ADBSat",
    "url": "https://github.com/nhcrisp/ADBSat",
    "data": {
        "doi": [
            "https://ui.adsabs.harvard.edu/abs/2021AcAau.187..475C",
            "https://ui.adsabs.harvard.edu/abs/2022CoPhC.27508326S",
            "https://ui.adsabs.harvard.edu/abs/2022ascl.soft04015S/abstract"
        ],
        "title": "ADBSat: Aerodynamic Database for Satellites",
        "url": "https://github.com/nhcrisp/ADBSat",
        "name": "ADBSat",
        "full_name": "nhcrisp/ADBSat",
        "html_url": "https://github.com/nhcrisp/ADBSat",
        "description": "Aerodynamic Database for Satellites",
        "created_at": "2020-07-16T11:41:03Z",
        "updated_at": "2022-05-24T16:50:08Z",
        "clone_url": "https://github.com/nhcrisp/ADBSat.git",
        "size": 3253,
        "stargazers_count": 5,
        "watchers_count": 5,
        "language": "MATLAB",
        "license": {
            "key": "gpl-3.0",
            "name": "GNU General Public License v3.0",
            "spdx_id": "GPL-3.0",
            "url": "https://api.github.com/licenses/gpl-3.0",
            "node_id": "MDc6TGljZW5zZTk="
        },
        "subscribers_count": 2,
        "owner": {
            "html_url": "https://github.com/nhcrisp",
            "avatar_url": "https://avatars.githubusercontent.com/u/40802736?v=4",
            "login": "nhcrisp",
            "type": "User"
        },
        "timestamp": "2022-07-17 16:31:15.521765",
        "avatar": "https://avatars.githubusercontent.com/u/40802736?v=4"
    }
}