{"parser": "github", "uid": "github/mingzehuang/latentcor", "url": "https://github.com/mingzehuang/latentcor", "data": {"timestamp": "2021-09-26 00:35:53.970075", "name": "latentcor", "url": "https://api.github.com/repos/mingzehuang/latentcor", "full_name": "mingzehuang/latentcor", "html_url": "https://github.com/mingzehuang/latentcor", "private": false, "description": "latentcor is an R package provides estimation for latent correlation with mixed data types (continuous, binary, truncated and ternary).", "created_at": "2021-02-05T15:05:33Z", "updated_at": "2021-09-25T14:49:09Z", "clone_url": "https://github.com/mingzehuang/latentcor.git", "homepage": "https://mingzehuang.github.io/latentcor/", "size": 121764, "stargazers_count": 5, "watchers_count": 5, "language": "R", "open_issues_count": 0, "license": {"key": "gpl-3.0", "name": "GNU General Public License v3.0", "spdx_id": "GPL-3.0", "url": "https://api.github.com/licenses/gpl-3.0", "node_id": "MDc6TGljZW5zZTk="}, "subscribers_count": 3, "owner": {"html_url": "https://github.com/mingzehuang", "avatar_url": "https://avatars.githubusercontent.com/u/70076112?v=4", "login": "mingzehuang", "type": "User"}, "topics": ["statistics", "data-science", "mixed-types", "r", "data-analysis", "data-mining", "machine-learning", "data-structures", "data-processing"]}, "doi": "https://doi.org/10.5281/zenodo.5517823"}
