{"parser": "github", "uid": "github/manulera/OpenCloning_frontend", "url": "https://github.com/manulera/OpenCloning_frontend", "data": {"name": "OpenCloning_frontend", "url": "https://github.com/manulera/OpenCloning_frontend", "full_name": "manulera/OpenCloning_frontend", "html_url": "https://github.com/manulera/OpenCloning_frontend", "private": false, "description": "The frontend application for OpenCloning", "created_at": "2021-10-04T11:48:28Z", "updated_at": "2025-03-27T16:06:58Z", "clone_url": "https://github.com/manulera/OpenCloning_frontend.git", "homepage": "https://opencloning.org/", "size": 4032, "stargazers_count": 1, "watchers_count": 1, "language": "JavaScript", "open_issues_count": 46, "license": {"key": "mit", "name": "MIT License", "spdx_id": "MIT", "url": "https://api.github.com/licenses/mit", "node_id": "MDc6TGljZW5zZTEz"}, "subscribers_count": 3, "owner": {"html_url": "https://github.com/manulera", "avatar_url": "https://avatars.githubusercontent.com/u/22526102?v=4", "login": "manulera", "type": "User"}, "topics": [], "timestamp": "2025-04-13 02:14:18.962186", "avatar": "https://avatars.githubusercontent.com/u/22526102?v=4"}}
