{
    "parser": "github",
    "uid": "github/Open-ET/flux-data-qaqc",
    "url": "https://github.com/Open-ET/flux-data-qaqc",
    "data": {
        "timestamp": "2021-10-17 00:34:53.448968",
        "name": "flux-data-qaqc",
        "url": "https://api.github.com/repos/Open-ET/flux-data-qaqc",
        "full_name": "Open-ET/flux-data-qaqc",
        "html_url": "https://github.com/Open-ET/flux-data-qaqc",
        "private": false,
        "description": "Energy Balance Closure Analysis and Eddy Flux Data Post-Processing",
        "created_at": "2019-04-17T22:02:38Z",
        "updated_at": "2021-10-15T21:56:23Z",
        "clone_url": "https://github.com/Open-ET/flux-data-qaqc.git",
        "homepage": "",
        "size": 75030,
        "stargazers_count": 1,
        "watchers_count": 1,
        "language": "Python",
        "open_issues_count": 0,
        "license": {
            "key": "bsd-3-clause",
            "name": "BSD 3-Clause \"New\" or \"Revised\" License",
            "spdx_id": "BSD-3-Clause",
            "url": "https://api.github.com/licenses/bsd-3-clause",
            "node_id": "MDc6TGljZW5zZTU="
        },
        "subscribers_count": 9,
        "owner": {
            "html_url": "https://github.com/Open-ET",
            "avatar_url": "https://avatars.githubusercontent.com/u/18035656?v=4",
            "login": "Open-ET",
            "type": "Organization"
        },
        "topics": []
    },
    "doi": "https://doi.org/10.5281/zenodo.5573104"
}