{"parser": "github", "uid": "github/david-mathews-1994/deltarice", "url": "https://github.com/david-mathews-1994/deltarice", "data": {"doi": "https://doi.org/10.5281/zenodo.11490673", "name": "deltarice", "url": "https://github.com/david-mathews-1994/deltarice", "full_name": "david-mathews-1994/deltarice", "html_url": "https://github.com/david-mathews-1994/deltarice", "description": "A high-performance compression library optimized for up-to 16-bit digitized analog signals", "created_at": "2023-10-03T18:46:19Z", "updated_at": "2024-06-21T23:44:20Z", "clone_url": "https://github.com/david-mathews-1994/deltarice.git", "size": 4455, "language": "C", "license": {"key": "mit", "name": "MIT License", "spdx_id": "MIT", "url": "https://api.github.com/licenses/mit", "node_id": "MDc6TGljZW5zZTEz"}, "subscribers_count": 1, "owner": {"html_url": "https://github.com/david-mathews-1994", "avatar_url": "https://avatars.githubusercontent.com/u/120204754?v=4", "login": "david-mathews-1994", "type": "User"}, "timestamp": "2024-06-23 00:38:33.605022", "avatar": "https://avatars.githubusercontent.com/u/120204754?v=4"}}
